.nxdtest
CHANGELOG.rst
COPYING
MANIFEST.in
README.rst
pyproject.toml
setup.py
tox.ini
trun
3rdparty/include/linux/list.h
golang/__init__.pxd
golang/__init__.py
golang/_context.pxd
golang/_context.pyx
golang/_cxx_test.pyx
golang/_errors.pxd
golang/_errors.pyx
golang/_errors_test.pyx
golang/_fmt.pxd
golang/_fmt.pyx
golang/_fmt_test.pyx
golang/_golang.pxd
golang/_golang.pyx
golang/_golang_test.pyx
golang/_gopath.py
golang/_gopath_test.py
golang/_io.pxd
golang/_io.pyx
golang/_os.pxd
golang/_os.pyx
golang/_os_test.pyx
golang/_strings_test.pyx
golang/_sync.pxd
golang/_sync.pyx
golang/_sync_test.pyx
golang/_testing.h
golang/_time.pxd
golang/_time.pyx
golang/context.cpp
golang/context.h
golang/context.pxd
golang/context.py
golang/context_test.py
golang/cxx.h
golang/cxx.pxd
golang/cxx_test.cpp
golang/cxx_test.py
golang/errors.cpp
golang/errors.h
golang/errors.pxd
golang/errors.py
golang/errors_test.cpp
golang/errors_test.py
golang/fmt.cpp
golang/fmt.h
golang/fmt.pxd
golang/fmt.py
golang/fmt_test.cpp
golang/fmt_test.py
golang/gcompat.py
golang/golang_test.py
golang/io.cpp
golang/io.h
golang/io.pxd
golang/io.py
golang/io_test.py
golang/libgolang.h
golang/os.cpp
golang/os.h
golang/os.pxd
golang/os_test.cpp
golang/os_test.py
golang/strconv.py
golang/strconv_test.py
golang/strings.cpp
golang/strings.h
golang/strings.pxd
golang/strings_test.cpp
golang/strings_test.py
golang/sync.cpp
golang/sync.h
golang/sync.pxd
golang/sync.py
golang/sync_test.cpp
golang/sync_test.py
golang/syscall.py
golang/testing.py
golang/time.cpp
golang/time.h
golang/time.pxd
golang/time.py
golang/time_test.py
golang/_patch/__init__.py
golang/_patch/ipython_py2.py
golang/_patch/pytest_py2.py
golang/cmd/__init__.py
golang/cmd/pybench.py
golang/os/__init__.py
golang/os/_signal.pxd
golang/os/_signal.pyx
golang/os/signal.cpp
golang/os/signal.h
golang/os/signal.pxd
golang/os/signal.py
golang/os/signal_test.py
golang/os/testprog/signal_test_all.py
golang/pyx/__init__.py
golang/pyx/_runtime_test.pyx
pygolang.egg-info/PKG-INFO
pygolang.egg-info/SOURCES.txt
pygolang.egg-info/dependency_links.txt
pygolang.egg-info/entry_points.txt
pygolang.egg-info/not-zip-safe
pygolang.egg-info/requires.txt
pygolang.egg-info/top_level.txt