Metadata-Version: 2.1
Name: pygolang
Version: 0.1
Summary: Go-like features for Python and Cython
Home-page: https://pygolang.nexedi.com
Author: Kirill Smelkov
Author-email: kirr@nexedi.com
License: GPLv3+ with wide exception for Open-Source
Project-URL: Bug Tracker, https://lab.nexedi.com/nexedi/pygolang/issues
Project-URL: Source Code, https://lab.nexedi.com/nexedi/pygolang
Project-URL: Documentation, https://pypi.org/project/pygolang
Keywords: golang go channel goroutine concurrency GOPATH python import gpython gevent cython nogil GIL
Platform: UNKNOWN
Classifier: Development Status :: 4 - Beta
Classifier: Intended Audience :: Developers
Classifier: Programming Language :: Python
Classifier: Programming Language :: Cython
Classifier: Programming Language :: Python :: 2
Classifier: Programming Language :: Python :: 2.7
Classifier: Programming Language :: Python :: 3
Classifier: Programming Language :: Python :: 3.5
Classifier: Programming Language :: Python :: 3.6
Classifier: Programming Language :: Python :: 3.7
Classifier: Programming Language :: Python :: 3.8
Classifier: Programming Language :: Python :: 3.9
Classifier: Programming Language :: Python :: Implementation :: CPython
Classifier: Programming Language :: Python :: Implementation :: PyPy
Classifier: Topic :: Software Development :: Interpreters
Classifier: Topic :: Software Development :: Libraries :: Python Modules
Provides-Extra: all
Provides-Extra: all_test
Provides-Extra: cmd.pybench
Provides-Extra: pyx.build
Provides-Extra: x.perf.benchlib
License-File: COPYING
